{
  "family_name": "Monacanthidae",
  "order_name": "Tetraodontiformes",
  "gbif_id": 5896,
  "sensory_modalities": {
    "vision": {
      "presence": "common",
      "notes": "Likely important for foraging and navigation in their tropical to subtropical marine habitats. Inference based on general fish biology and habitat, although specific visual adaptations are unknown from the provided context.",
      "inferred_from_species": [],
      "frequency_range_hz": {
        "min": 430000000000000.0,
        "max": 750000000000000.0
      }
    },
    "mechanoreception": {
      "presence": "common",
      "notes": "Lateral line system likely present, enabling detection of water movement and pressure changes. Important for predator avoidance and schooling (if applicable).",
      "inferred_from_species": [],
      "frequency_range_hz": {
        "min": 1.0,
        "max": 1000.0
      }
    },
    "chemoreception": {
      "presence": "common",
      "notes": "Olfaction and taste likely play a role in food detection. General to fish biology.",
      "inferred_from_species": [],
      "frequency_range_hz": {
        "min": 0.0001,
        "max": 1.0
      }
    }
  },
  "confidence": "MEDIUM",
  "sources": [
    "https://en.wikipedia.org/wiki/Monacanthidae",
    "https://en.wikipedia.org/wiki/Thamnaconus_modestus",
    "https://en.wikipedia.org/wiki/Thamnaconus_hypargyreus"
  ],
  "generated_at": "2026-01-04T10:26:03.651317"
}